salure_helpers/__init__.py
salure_helpers/clickhouse.py
salure_helpers/elastic.py
salure_helpers/ftp.py
salure_helpers/logger.py
salure_helpers/mail_client.py
salure_helpers/mysql.py
salure_helpers/pgp_encryption.py
salure_helpers/planning_nl.py
salure_helpers/profit.py
salure_helpers/profit_mutations.py
salure_helpers/salure_functions.py
salure_helpers/sharepoint.py
salure_helpers/somtoday.py
salure_helpers/sqlite.py
salure_helpers/task_scheduler.py
salure_helpers/vospiegel.py
salure_helpers/zermelo.py
salure_helpers/datasets/country_isocodes.csv
salure_helpers/datasets/languages_isocodes.csv
salure_helpers/templates/mail_salureconnect.html
salure_helpers-10.6.6.dist-info/METADATA
salure_helpers-10.6.6.dist-info/WHEEL
salure_helpers-10.6.6.dist-info/top_level.txt
salure_helpers-10.6.6.dist-info/RECORD
