Metadata-Version: 2.1
Name: salure-helpers
Version: 10.6.6
Summary: Files with helpful code, developed by Salure
Home-page: https://bitbucket.org/salurebi/salure_helpers/
Author: Salure
Author-email: bi@salure.nl
License: Salure License
Platform: UNKNOWN
Requires-Dist: pandas
Requires-Dist: mandrill-really-maintained
Requires-Dist: pymysql
Requires-Dist: requests
Requires-Dist: pysftp
Requires-Dist: pyarrow
Requires-Dist: twine
Requires-Dist: clickhouse-driver
Requires-Dist: fs
Requires-Dist: python-gnupg
Requires-Dist: xmltodict
Requires-Dist: zeep
